NotionPy/__init__.py
NotionPy/constants.py
NotionPy/create.py
NotionPy/notionpy.py
NotionPy/query.py
NotionPy/update.py
NotionPy/utils.py
auto_py_notion-0.1.2.dist-info/LICENSE
auto_py_notion-0.1.2.dist-info/METADATA
auto_py_notion-0.1.2.dist-info/WHEEL
auto_py_notion-0.1.2.dist-info/top_level.txt
auto_py_notion-0.1.2.dist-info/RECORD
