Metadata-Version: 2.1
Name: auto-py-notion
Version: 0.1.2
Summary: integrate notion api with your workflow
Home-page: https://github.com/kareemmahlees/NotionPy
Author: Kareem Ebrahim
Author-email: kareemmahlees@gmail.com
License: MIT
Platform: UNKNOWN
Classifier: License :: OSI Approved :: MIT License
Classifier: Programming Language :: Python :: 3
Classifier: Programming Language :: Python :: 3.10
License-File: LICENSE
Requires-Dist: requests
